GoogleAdsWindsorApi/__init__.py
GoogleAdsWindsorApi/client.py
GoogleAdsWindsorApi/enums.py
test/__init__.py
test/tests.py
GoogleAdsWindsorApi-1.0.6.dist-info/METADATA
GoogleAdsWindsorApi-1.0.6.dist-info/WHEEL
GoogleAdsWindsorApi-1.0.6.dist-info/top_level.txt
GoogleAdsWindsorApi-1.0.6.dist-info/RECORD
