Metadata-Version: 2.1
Name: GoogleAdsWindsorApi
Version: 1.0.6
Summary: Easy access to windsor.ai Google Ads APIs
Home-page: https://github.com/windsor-ai/GoogleAdsWindsorApi
Author: Windsor AI
Author-email: dev@windsor.ai
Requires-Dist: requests (~=2.25.1)
